plover_stroke.py
_plover_stroke.cpython-37m-i386-linux-gnu.so
plover_stroke-1.1.0.dist-info/WHEEL
plover_stroke-1.1.0.dist-info/zip-safe
plover_stroke-1.1.0.dist-info/top_level.txt
plover_stroke-1.1.0.dist-info/METADATA
plover_stroke-1.1.0.dist-info/RECORD
