Metadata-Version: 2.1
Name: plover-stroke
Version: 1.1.0
Summary: Stroke handling helper library for Plover
Home-page: https://github.com/benoit-pierre/plover_stroke
Author: Benoit Pierre
Author-email: benoit.pierre@gmail.com
License: GNU General Public License v2 or later (GPLv2+)
Project-URL: Source Code, https://github.com/benoit-pierre/plover_stroke
Project-URL: Issue Tracker, https://github.com/benoit-pierre/plover_stroke/issues
Keywords: plover
Classifier: Development Status :: 4 - Beta
Classifier: Intended Audience :: End Users/Desktop
Classifier: License :: OSI Approved :: GNU General Public License v2 or later (GPLv2+)
Classifier: Operating System :: OS Independent
Classifier: Programming Language :: Python :: 3
Classifier: Programming Language :: Python :: 3.6
Classifier: Programming Language :: Python :: 3.7
Classifier: Programming Language :: Python :: 3.8
Classifier: Programming Language :: Python :: 3.9
Classifier: Programming Language :: Python :: 3.10
Requires-Python: >=3.6
Provides-Extra: test
